robot_desktop/__init__.py
robot_desktop/application.py
robot_desktop/clipboard.py
robot_desktop/extract_icon.py
robot_desktop/extract_icon_main.py
robot_desktop/find_by_xpath.py
robot_desktop/index.py
robot_desktop/windows_inspect.py
robot_desktop/windows_inspect_main.py
robot_desktop/windows_pick.py
robot_desktop-0.3.0.dist-info/METADATA
robot_desktop-0.3.0.dist-info/WHEEL
robot_desktop-0.3.0.dist-info/RECORD
