Metadata-Version: 2.4
Name: robot_desktop
Version: 0.3.0
Summary: robot desktop tools
Author: mance
Classifier: License :: OSI Approved :: MIT License
Classifier: Operating System :: OS Independent
Classifier: Programming Language :: Python :: 3
Requires-Python: >=3.11
Requires-Dist: jinja2
Requires-Dist: psutil
Requires-Dist: py-dom-xpath-six
Requires-Dist: pyautogui
Requires-Dist: pynput
Requires-Dist: pyperclip
Requires-Dist: pywin32
Requires-Dist: uiautomation
Requires-Dist: websocket-client
Requires-Dist: websockets
